<?xml version="1.0" encoding="UTF-8"?>
<egyptian
  creator="Mark-Jan Nederhof"
  name="Sethe"
  labelname=""
  created="2015-08-06"
  modified=""
  version=""
  scheme=""
  language=""
  upload=""
  email=""
  password=""
>
<header>
<p>
Transcription of the inscription of count Reni,
following Sethe (1927), number 25 (pp. 74-75).
</p>
</header>
<bibliography>
<li>
K. Sethe. <i>Urkunden der 18. Dynastie, Volume I</i>. Hinrichs,
Leipzig, 1927.
</li>
</bibliography>
<tier name="hieroglyphic" mode="shown"/>
<tier name="transliteration" mode="ignored"/>
<tier name="translation" mode="ignored"/>
<tier name="lexical" mode="ignored"/>
<segment>
<texthi>
<coord id="1"/>[hlr]M23*X8-R4:[sep=0.5](.:[sep=0.0]X1)*Q3-M22-[sep=0.5]D58-(W24:X1)*T3-X1:O48-D37:O34-Aa1*[sep=0.5]X1:[sep=0.5]V30:[sep=0.5]X1-F35-[sep=0.5]X1-D60-X1-O1:[sep=0.5]D21:[sep=0.5]D21-X1*(D2:Z1)-R3-O34-G17-D1:Z1-X1:D21
</texthi>
</segment>

<segment>
<texthi>
<coord id="2"/>[hlr]M17*M6-N5:V30-N35:N1-N35:[sep=0.5]D28*[sep=0.5]Z1:[sep=0.5]N35-F4:[sep=0.5]D36-Y4*M17-[sep=0.5]N29:D21-N35-R8*F35-F5:[sep=0.5]Y1-D2:Z1-G17-N37:[sep=0.5]X1*[sep=0.5]M17*[sep=0.5]M17-X1-V30:X1-D21:N35-M17-Aa11:P8[rotate=270]
</texthi>
</segment>

<segment>
<texthi>
<coord id="3"/>[hlr]insert[bs](I10,D46)-[sep=0.5]I9-M17*G43-T18*S29-D54:N35-A41-N35-D21:V31-insert[ts,sep=0.4](modify[height=1.0](empty[width=0.0,height=0.2]:D56*[sep=0.5,fit]X1),D1)-A24-N35-N35:I9
</texthi>
</segment>

<segment>
<texthi>
<coord id="4"/>[hlr]A17-D53-O34-M12-M17*[sep=0.5]M17-A2-A1-L1-G17-O11-D36:O1
</texthi>
</segment>

<segment>
<texthi>
<coord id="5"/>[hlr]D21:[sep=0.5]Aa1:[sep=0.5]Y1-N35-G43-G5-G17-O1*Z1:I9-F22:N35-A19-G17[shade]
</texthi>
</segment>

<segment>
<texthi>
<coord id="6"/>[hlr]O49:[sep=0.5]X1*Z1-(F34:Z1)*(D2:Z1)-Aa1:D21-Q3:[sep=0.5]D40-D21-G29-V31:N35-M23*X1-A40
</texthi>
</segment>

<segment>
<texthi>
<coord id="7"/>[hlr]D35-F32:O34-D2:[sep=0.5]F34-D35-L1*(O34:Q3*O50)-D21:N35-F35-Aa15-N17:N21-D21-[sep=0.5]M36:D21-I9-F4:[sep=0.5]D36-F20-R8*![shade]U36*[sep=0.5](Z1:[sep=0.5]Z1:[sep=0.5]Z1)
</texthi>
</segment>

<segment>
<texthi>
<coord id="8"/>[hlr]N35-M22-[sep=0.5]D58*(X1:O49)-D21:[sep=0.5]N35:[sep=0.5]Z4-A52-Aa11[rotate=270]*P8-D4:N35-F4:[sep=0.5]D36-I5a:D40-[sep=0.5]![shade]A52-[sep=0.5]Aa11[rotate=270]*[sep=0.5]P8
</texthi>
</segment>
</egyptian>
